Metadata-Version: 1.1
Name: flake8-max-lines
Version: 0.0.2
Summary: flake8 plugin to check max lines per files
Home-page: https://github.com/misogihagi/flake8_max_lines
Author: misogihagi
Author-email: hagimiso@gmail.com
License: MIT
Platform: UNKNOWN
Classifier: Framework :: Flake8
Classifier: Environment :: Console
Classifier: Intended Audience :: Developers
Classifier: License :: OSI Approved :: MIT License
Classifier: Programming Language :: Python
Classifier: Programming Language :: Python :: 3
Classifier: Topic :: Software Development :: Libraries :: Python Modules
Classifier: Topic :: Software Development :: Quality Assurance
